fluxbfl/__init__.py
fluxbfl/__main__.py
fluxbfl/_version.py
fluxbfl/cli.py
fluxbfl/cli_control.py
fluxbfl/cli_fill.py
fluxbfl/cli_kontext.py
fluxbfl/cli_redux.py
fluxbfl/content_filters.py
fluxbfl/math.py
fluxbfl/model.py
fluxbfl/sampling.py
fluxbfl/util.py
fluxbfl/modules/autoencoder.py
fluxbfl/modules/conditioner.py
fluxbfl/modules/image_embedders.py
fluxbfl/modules/layers.py
fluxbfl/modules/lora.py
fluxbfl/trt/__init__.py
fluxbfl/trt/trt_manager.py
fluxbfl/trt/engine/__init__.py
fluxbfl/trt/engine/base_engine.py
fluxbfl/trt/engine/clip_engine.py
fluxbfl/trt/engine/t5_engine.py
fluxbfl/trt/engine/transformer_engine.py
fluxbfl/trt/engine/vae_engine.py
fluxbfl/trt/trt_config/__init__.py
fluxbfl/trt/trt_config/base_trt_config.py
fluxbfl/trt/trt_config/clip_trt_config.py
fluxbfl/trt/trt_config/t5_trt_config.py
fluxbfl/trt/trt_config/transformer_trt_config.py
fluxbfl/trt/trt_config/vae_trt_config.py
fluxbfl-0.0.3.dist-info/licenses/LICENSE
fluxbfl-0.0.3.dist-info/METADATA
fluxbfl-0.0.3.dist-info/WHEEL
fluxbfl-0.0.3.dist-info/top_level.txt
fluxbfl-0.0.3.dist-info/RECORD
