Metadata-Version: 2.4
Name: fluxbfl
Version: 0.0.3
Summary: Inference codebase for FLUX
Author-email: Black Forest Labs <support@blackforestlabs.ai>
Requires-Python: >=3.10
License-File: LICENSE
Requires-Dist: einops
Dynamic: license-file
